{"config": {"view": {"width": 400, "height": 300}}, "hconcat": [{"layer": [{"data": {"values": [{"TargetValue": 0.8, "Title": "Target"}]}, "mark": {"type": "rule", "strokeDash": [4, 2], "strokeWidth": 1}, "encoding": {"color": {"value": "#2ca02c"}, "y": {"type": "quantitative", "field": "TargetValue"}}}, {"data": {"values": [{"Percentage": 0.3014, "Date": "2018-04-23"}, {"Percentage": 0.3702, "Date": "2018-07-02"}, {"Percentage": 0.3349, "Date": "2018-06-05"}, {"Percentage": 0.2193, "Date": "2018-01-29"}, {"Percentage": 0.3208, "Date": "2018-05-14"}, {"Percentage": 0.3628, "Date": "2018-06-25"}, {"Percentage": 0.2164, "Date": "2017-12-18"}, {"Percentage": 0.2729, "Date": "2018-03-19"}, {"Percentage": 0.2835, "Date": "2018-04-02"}, {"Percentage": 0.3895, "Date": "2018-07-23"}, {"Percentage": 0.1956, "Date": "2017-10-09"}, {"Percentage": 0.2511, "Date": "2018-02-19"}, {"Percentage": 0.2203, "Date": "2018-01-08"}, {"Percentage": 0.3977, "Date": "2018-08-13"}, {"Percentage": 0.2252, "Date": "2018-01-22"}, {"Percentage": 0.2009, "Date": "2017-10-23"}, {"Percentage": 0.3301, "Date": "2018-05-28"}, {"Percentage": 0.204, "Date": "2017-09-11"}, {"Percentage": 0.222, "Date": "2018-01-15"}, {"Percentage": 0.3738, "Date": "2018-07-09"}, {"Percentage": 0.2057, "Date": "2017-11-13"}, {"Percentage": 0.1879, "Date": "2017-08-21"}, {"Percentage": 0.3515, "Date": "2018-06-18"}, {"Percentage": 0.193, "Date": "2017-10-02"}, {"Percentage": 0.2442, "Date": "2018-02-12"}, {"Percentage": 0.2361, "Date": "2018-02-05"}, {"Percentage": 0.2699, "Date": "2018-03-12"}, {"Percentage": 0.2635, "Date": "2018-03-05"}, {"Percentage": 0.2897, "Date": "2018-04-09"}, {"Percentage": 0.2108, "Date": "2017-12-04"}, {"Percentage": 0.203, "Date": "2017-10-30"}, {"Percentage": 0.2192, "Date": "2018-01-01"}, {"Percentage": 0.1914, "Date": "2017-09-25"}, {"Percentage": 0.2966, "Date": "2018-04-16"}, {"Percentage": 0.2168, "Date": "2017-12-26"}, {"Percentage": 0.2133, "Date": "2017-12-11"}, {"Percentage": 0.1996, "Date": "2017-10-16"}, {"Percentage": 0.2559, "Date": "2018-02-26"}, {"Percentage": 0.1893, "Date": "2017-09-04"}, {"Percentage": 0.2782, "Date": "2018-03-26"}, {"Percentage": 0.2045, "Date": "2017-11-06"}, {"Percentage": 0.3776, "Date": "2018-07-16"}, {"Percentage": 0.3085, "Date": "2018-04-30"}, {"Percentage": 0.3124, "Date": "2018-05-07"}, {"Percentage": 0.3934, "Date": "2018-08-06"}, {"Percentage": 0.3353, "Date": "2018-06-11"}, {"Percentage": 0.3904, "Date": "2018-07-30"}, {"Percentage": 0.1885, "Date": "2017-08-28"}, {"Percentage": 0.3253, "Date": "2018-05-21"}, {"Percentage": 0.1915, "Date": "2017-09-18"}, {"Percentage": 0.4014, "Date": "2018-08-20"}]}, "mark": {"type": "line", "strokeWidth": 2}, "encoding": {"color": {"value": "#aec7e8"}, "x": {"type": "temporal", "field": "Date", "title": ""}, "y": {"type": "quantitative", "field": "Percentage"}}}, {"data": {"values": [{"Percentage": 0.3385, "Date": "2018-04-23"}, {"Percentage": 0.3578, "Date": "2018-07-02"}, {"Percentage": 0.3554, "Date": "2018-06-05"}, {"Percentage": 0.2898, "Date": "2018-01-29"}, {"Percentage": 0.343, "Date": "2018-05-14"}, {"Percentage": 0.3616, "Date": "2018-06-25"}, {"Percentage": 0.2908, "Date": "2017-12-18"}, {"Percentage": 0.3202, "Date": "2018-03-19"}, {"Percentage": 0.3289, "Date": "2018-04-02"}, {"Percentage": 0.3584, "Date": "2018-07-23"}, {"Percentage": 0.2765, "Date": "2017-10-09"}, {"Percentage": 0.2898, "Date": "2018-02-19"}, {"Percentage": 0.2847, "Date": "2018-01-08"}, {"Percentage": 0.3687, "Date": "2018-08-13"}, {"Percentage": 0.288, "Date": "2018-01-22"}, {"Percentage": 0.2857, "Date": "2017-10-23"}, {"Percentage": 0.3519, "Date": "2018-05-28"}, {"Percentage": 0.2753, "Date": "2017-09-11"}, {"Percentage": 0.2913, "Date": "2018-01-15"}, {"Percentage": 0.3578, "Date": "2018-07-09"}, {"Percentage": 0.285, "Date": "2017-11-13"}, {"Percentage": 0.2768, "Date": "2017-08-21"}, {"Percentage": 0.363, "Date": "2018-06-18"}, {"Percentage": 0.2765, "Date": "2017-10-02"}, {"Percentage": 0.2888, "Date": "2018-02-12"}, {"Percentage": 0.2904, "Date": "2018-02-05"}, {"Percentage": 0.3165, "Date": "2018-03-12"}, {"Percentage": 0.3048, "Date": "2018-03-05"}, {"Percentage": 0.3348, "Date": "2018-04-09"}, {"Percentage": 0.2879, "Date": "2017-12-04"}, {"Percentage": 0.2883, "Date": "2017-10-30"}, {"Percentage": 0.2889, "Date": "2018-01-01"}, {"Percentage": 0.2772, "Date": "2017-09-25"}, {"Percentage": 0.3415, "Date": "2018-04-16"}, {"Percentage": 0.2916, "Date": "2017-12-26"}, {"Percentage": 0.289, "Date": "2017-12-11"}, {"Percentage": 0.285, "Date": "2017-10-16"}, {"Percentage": 0.2941, "Date": "2018-02-26"}, {"Percentage": 0.2746, "Date": "2017-09-04"}, {"Percentage": 0.3238, "Date": "2018-03-26"}, {"Percentage": 0.2891, "Date": "2017-11-06"}, {"Percentage": 0.357, "Date": "2018-07-16"}, {"Percentage": 0.3392, "Date": "2018-04-30"}, {"Percentage": 0.34, "Date": "2018-05-07"}, {"Percentage": 0.365, "Date": "2018-08-06"}, {"Percentage": 0.3563, "Date": "2018-06-11"}, {"Percentage": 0.3636, "Date": "2018-07-30"}, {"Percentage": 0.276, "Date": "2017-08-28"}, {"Percentage": 0.3503, "Date": "2018-05-21"}, {"Percentage": 0.276, "Date": "2017-09-18"}, {"Percentage": 0.3687, "Date": "2018-08-20"}]}, "mark": {"type": "line", "strokeWidth": 2}, "encoding": {"color": {"value": "#ffbb78"}, "x": {"type": "temporal", "field": "Date", "title": ""}, "y": {"type": "quantitative", "field": "Percentage"}}}, {"data": {"values": [{"Percentage": 0.2302, "Date": "2018-04-23"}, {"Percentage": 0.2403, "Date": "2018-07-02"}, {"Percentage": 0.2441, "Date": "2018-06-05"}, {"Percentage": 0.208, "Date": "2018-01-29"}, {"Percentage": 0.2362, "Date": "2018-05-14"}, {"Percentage": 0.2422, "Date": "2018-06-25"}, {"Percentage": 0.2047, "Date": "2017-12-18"}, {"Percentage": 0.2222, "Date": "2018-03-19"}, {"Percentage": 0.2283, "Date": "2018-04-02"}, {"Percentage": 0.2385, "Date": "2018-07-23"}, {"Percentage": 0.1905, "Date": "2017-10-09"}, {"Percentage": 0.2126, "Date": "2018-02-19"}, {"Percentage": 0.2063, "Date": "2018-01-08"}, {"Percentage": 0.2366, "Date": "2018-08-13"}, {"Percentage": 0.2063, "Date": "2018-01-22"}, {"Percentage": 0.1935, "Date": "2017-10-23"}, {"Percentage": 0.246, "Date": "2018-05-28"}, {"Percentage": 0.192, "Date": "2017-09-11"}, {"Percentage": 0.2063, "Date": "2018-01-15"}, {"Percentage": 0.2403, "Date": "2018-07-09"}, {"Percentage": 0.2016, "Date": "2017-11-13"}, {"Percentage": 0.192, "Date": "2017-08-21"}, {"Percentage": 0.2441, "Date": "2018-06-18"}, {"Percentage": 0.1905, "Date": "2017-10-02"}, {"Percentage": 0.2063, "Date": "2018-02-12"}, {"Percentage": 0.208, "Date": "2018-02-05"}, {"Percentage": 0.2222, "Date": "2018-03-12"}, {"Percentage": 0.2143, "Date": "2018-03-05"}, {"Percentage": 0.2266, "Date": "2018-04-09"}, {"Percentage": 0.2063, "Date": "2017-12-04"}, {"Percentage": 0.2016, "Date": "2017-10-30"}, {"Percentage": 0.2063, "Date": "2018-01-01"}, {"Percentage": 0.192, "Date": "2017-09-25"}, {"Percentage": 0.2283, "Date": "2018-04-16"}, {"Percentage": 0.2063, "Date": "2017-12-26"}, {"Percentage": 0.2047, "Date": "2017-12-11"}, {"Percentage": 0.192, "Date": "2017-10-16"}, {"Percentage": 0.2126, "Date": "2018-02-26"}, {"Percentage": 0.192, "Date": "2017-09-04"}, {"Percentage": 0.2205, "Date": "2018-03-26"}, {"Percentage": 0.2016, "Date": "2017-11-06"}, {"Percentage": 0.2385, "Date": "2018-07-16"}, {"Percentage": 0.2362, "Date": "2018-04-30"}, {"Percentage": 0.2362, "Date": "2018-05-07"}, {"Percentage": 0.2366, "Date": "2018-08-06"}, {"Percentage": 0.2441, "Date": "2018-06-11"}, {"Percentage": 0.2385, "Date": "2018-07-30"}, {"Percentage": 0.192, "Date": "2017-08-28"}, {"Percentage": 0.2441, "Date": "2018-05-21"}, {"Percentage": 0.192, "Date": "2017-09-18"}, {"Percentage": 0.2385, "Date": "2018-08-20"}]}, "mark": {"type": "line", "strokeWidth": 4}, "encoding": {"color": {"value": "#9467bd"}, "x": {"type": "temporal", "field": "Date", "title": ""}, "y": {"type": "quantitative", "axis": {"format": "%", "title": ""}, "field": "Percentage", "scale": {"domain": [0, 1]}}}, "height": 200, "width": 200}]}, {"layer": [{"data": {"values": [{"Percentage": 0.6613}, {"Percentage": 0.7843}, {"Percentage": 0.7615}, {"Percentage": 0.0909}, {"Percentage": 0.2}, {"Percentage": 0.5333}, {"Percentage": 0.2385}, {"Percentage": 0.6667}, {"Percentage": 0.374}, {"Percentage": 0.3117}, {"Percentage": 0.4516}, {"Percentage": 0.225}, {"Percentage": 0.125}, {"Percentage": 0.5714}, {"Percentage": 0.7534}, {"Percentage": 0.1286}, {"Percentage": 0.2281}, {"Percentage": 0.1915}, {"Percentage": 0.2143}, {"Percentage": 0.5294}, {"Percentage": 0.1333}, {"Percentage": 0.4412}, {"Percentage": 0.5263}, {"Percentage": 0.5}, {"Percentage": 0.4286}, {"Percentage": 0.6857}, {"Percentage": 0.25}, {"Percentage": 0.1348}, {"Percentage": 0.3529}, {"Percentage": 0.6705}, {"Percentage": 0.4153}, {"Percentage": 0.4727}, {"Percentage": 0.1287}, {"Percentage": 0.5161}, {"Percentage": 0.0864}, {"Percentage": 0.0714}, {"Percentage": 0.1899}, {"Percentage": 0.186}, {"Percentage": 0.2}, {"Percentage": 0.0507}, {"Percentage": 0.3818}, {"Percentage": 0.4318}, {"Percentage": 0.5556}, {"Percentage": 0.6}, {"Percentage": 0.3}, {"Percentage": 0.5417}, {"Percentage": 0.6}, {"Percentage": 0.2603}, {"Percentage": 0.2069}, {"Percentage": 0.4483}, {"Percentage": 0.3333}, {"Percentage": 0.2778}, {"Percentage": 0.3273}, {"Percentage": 0.5714}, {"Percentage": 0.2353}, {"Percentage": 0.5}, {"Percentage": 0.32}, {"Percentage": 0.1333}, {"Percentage": 0.1304}, {"Percentage": 0.6429}, {"Percentage": 0.5}, {"Percentage": 0.6552}, {"Percentage": 0.3333}, {"Percentage": 0.4706}, {"Percentage": 0.5862}, {"Percentage": 0.5733}, {"Percentage": 0.6429}, {"Percentage": 0.8214}, {"Percentage": 0.1429}]}, "mark": {"type": "tick", "color": "#ddd"}, "encoding": {"y": {"type": "quantitative", "axis": {"format": "%", "labels": false, "title": ""}, "field": "Percentage", "scale": {"domain": [0, 1]}}}, "height": 200}, {"data": {"values": [{"Percentage": 0.2385}]}, "mark": "tick", "encoding": {"color": {"value": "#9467bd"}, "opacity": {"value": "1.0"}, "y": {"type": "quantitative", "field": "Percentage"}}}, {"data": {"values": [{"Percentage": 0.2385}]}, "mark": {"type": "text", "align": "left", "baseline": "middle", "dx": 15, "size": 20}, "encoding": {"color": {"value": "#9467bd"}, "opacity": {"value": "1.0"}, "text": {"type": "quantitative", "field": "Percentage", "format": ".2%"}, "y": {"type": "quantitative", "field": "Percentage"}}}]}], "$schema": "https://vega.github.io/schema/vega-lite/v2.4.3.json"}